{"devicePlatform":"","logFolder":"C:\\Users\\hwanta\\Katalon Studio\\admin\\Reports\\login\\20180208_154746","runData":{"hostName":"hwanta - tt","os":"Windows 7 64bit","katalonVersion":"5.3.0.1","browser":"Chrome 63.0.3239.132","hostAddress":"10.77.236.189","sessionId":"d208b7fa2dcbd4b99b47fec8ff8708b5","seleniumVersion":"3.7.1","proxyInformation":"ProxyInformation{proxyOption\u003dNO_PROXY, proxyServerType\u003dHTTP, password\u003d, proxyServerAddress\u003d, proxyServerPort\u003d0}","platform":"Windows 7"},"type":"TEST_SUITE","name":"login","id":"Test Suites/login","source":"","message":"Test Cases/login FAILED because (of) Text \u0027hwanta\u0027 is not present on page ","description":"","startTime":1518072470047,"endTime":1518072484622,"childRecords":[{"isOptional":false,"type":"TEST_CASE","name":"Test Cases/login","id":"Test Cases/login","source":"C:\\\\Users\\\\hwanta\\\\Katalon Studio\\\\admin\\\\Test Cases\\\\login.tc","message":"Test Cases/login FAILED because (of) Text \u0027hwanta\u0027 is not present on page ","description":"","startTime":1518072470687,"endTime":1518072483706,"childRecords":[{"testStatus":{"stackTrace":"","statusValue":"INFO"},"type":"MESSAGE","name":"","message":"Evaluating variables for test case","startTime":1518072470724,"endTime":0,"childRecords":[],"interuppted":false},{"index":1,"isIgnoredIfFailed":false,"type":"TEST_STEP","name":"openBrowser","message":"Browser is opened with url: \u0027http://gdadmin.hwanta71.godomall.com/base/login.php\u0027","description":"","startTime":1518072471046,"endTime":1518072482804,"childRecords":[{"testStatus":{"stackTrace":"","statusValue":"PASSED"},"type":"MESSAGE","name":"","message":"Browser is opened with url: \u0027http://gdadmin.hwanta71.godomall.com/base/login.php\u0027","startTime":1518072482803,"endTime":0,"childRecords":[],"interuppted":false}],"interuppted":false},{"index":2,"isIgnoredIfFailed":false,"type":"TEST_STEP","name":"setText","message":"Text \u0027hwanta\u0027 is set on object \u0027Object Repository/login/input_managerId\u0027","description":"","startTime":1518072482804,"endTime":1518072483186,"childRecords":[{"testStatus":{"stackTrace":"","statusValue":"PASSED"},"type":"MESSAGE","name":"","message":"Text \u0027hwanta\u0027 is set on object \u0027Object Repository/login/input_managerId\u0027","startTime":1518072483185,"endTime":0,"childRecords":[],"interuppted":false}],"interuppted":false},{"index":3,"isIgnoredIfFailed":false,"type":"TEST_STEP","name":"setText","message":"Text \u0027xogudgodo!@\u0027 is set on object \u0027Object Repository/login/input_managerPw\u0027","description":"","startTime":1518072483186,"endTime":1518072483354,"childRecords":[{"testStatus":{"stackTrace":"","statusValue":"PASSED"},"type":"MESSAGE","name":"","message":"Text \u0027xogudgodo!@\u0027 is set on object \u0027Object Repository/login/input_managerPw\u0027","startTime":1518072483353,"endTime":0,"childRecords":[],"interuppted":false}],"interuppted":false},{"index":4,"isIgnoredIfFailed":false,"type":"TEST_STEP","name":"click","message":"Object: \u0027Object Repository/login/input_btn btn-black\u0027 is clicked on","description":"","startTime":1518072483354,"endTime":1518072483602,"childRecords":[{"testStatus":{"stackTrace":"","statusValue":"PASSED"},"type":"MESSAGE","name":"","message":"Object: \u0027Object Repository/login/input_btn btn-black\u0027 is clicked on","startTime":1518072483602,"endTime":0,"childRecords":[],"interuppted":false}],"interuppted":false},{"index":5,"isIgnoredIfFailed":false,"type":"TEST_STEP","name":"verifyTextPresent","message":"Text \u0027hwanta\u0027 is not present on page ","description":"","startTime":1518072483603,"endTime":1518072483700,"childRecords":[{"testStatus":{"stackTrace":"","statusValue":"FAILED"},"type":"MESSAGE","name":"","message":"Text \u0027hwanta\u0027 is not present on page ","startTime":1518072483699,"endTime":0,"childRecords":[],"interuppted":false}],"interuppted":false},{"testStatus":{"stackTrace":"","statusValue":"FAILED"},"type":"MESSAGE","name":"","message":"Test Cases/login FAILED because (of) Text \u0027hwanta\u0027 is not present on page ","startTime":1518072483701,"endTime":0,"childRecords":[],"interuppted":false}],"interuppted":false}],"interuppted":false}